taskiq_aio_kafka/__init__.py
taskiq_aio_kafka/broker.py
taskiq_aio_kafka/exceptions.py
taskiq_aio_kafka/models.py
taskiq_aio_kafka-0.2.2.dist-info/LICENSE
taskiq_aio_kafka-0.2.2.dist-info/METADATA
taskiq_aio_kafka-0.2.2.dist-info/WHEEL
taskiq_aio_kafka-0.2.2.dist-info/RECORD
