Metadata-Version: 2.3
Name: taskiq-aio-kafka
Version: 0.2.2
Summary: Kafka broker for taskiq
License: LICENSE
Keywords: taskiq,tasks,distributed,async,kafka,aiokafka
Author: Taskiq team
Author-email: taskiq@no-reply.com
Maintainer: Taskiq team
Maintainer-email: taskiq@no-reply.com
Requires-Python: >=3.9,<4.0
Classifier: Development Status :: 3 - Alpha
Classifier: Intended Audience :: Developers
Classifier: License :: Other/Proprietary License
Classifier: Operating System :: OS Independent
Classifier: Programming Language :: Python
Classifier: Programming Language :: Python :: 3
Classifier: Programming Language :: Python :: 3.9
Classifier: Programming Language :: Python :: 3.10
Classifier: Programming Language :: Python :: 3.11
Classifier: Programming Language :: Python :: 3.12
Classifier: Programming Language :: Python :: 3.13
Classifier: Programming Language :: Python :: 3 :: Only
Classifier: Programming Language :: Python :: 3.8
Classifier: Topic :: System :: Networking
Classifier: Typing :: Typed
Requires-Dist: aiokafka (>=0.10.0,<0.11.0)
Requires-Dist: kafka-python (>=2.0.2,<3.0.0)
Requires-Dist: taskiq (>=0,<1)
